phishing_hunter/__init__.py
phishing_hunter/api_client.py
phishing_hunter/configuration.py
phishing_hunter/exceptions.py
phishing_hunter/rest.py
phishing_hunter/schemas.py
phishing_hunter/model/__init__.py
phishing_hunter/models/__init__.py
phishing_hunter/paths/__init__.py
phishing_hunter/paths/apikey/__init__.py
phishing_hunter/paths/apikey/get.py
phishing_hunter/paths/apikey_create/__init__.py
phishing_hunter/paths/apikey_create/post.py
phishing_hunter/paths/apikey_delete/__init__.py
phishing_hunter/paths/apikey_delete/post.py
phishing_hunter/paths/apikeys/__init__.py
phishing_hunter/paths/apikeys/get.py
phishing_hunter/paths/apikeys/post.py
phishing_hunter/paths/hunting/__init__.py
phishing_hunter/paths/hunting/get.py
phishing_hunter/paths/hunting/post.py
phishing_hunter/paths/notify/__init__.py
phishing_hunter/paths/notify/get.py
phishing_hunter/paths/notify/post.py
phishing_hunter/paths/observation/__init__.py
phishing_hunter/paths/observation/get.py
phishing_hunter/paths/observation_add/__init__.py
phishing_hunter/paths/observation_add/post.py
phishing_hunter/paths/observation_remove/__init__.py
phishing_hunter/paths/observation_remove/post.py
phishing_hunter/paths/scanner/__init__.py
phishing_hunter/paths/scanner/get.py
phishing_hunter/paths/scanner_add/__init__.py
phishing_hunter/paths/scanner_add/post.py
phishing_hunter/paths/scanner_remove/__init__.py
phishing_hunter/paths/scanner_remove/post.py
phishing_hunter/paths/users_info/__init__.py
phishing_hunter/paths/users_info/get.py
phishing_hunter/ph/__init__.py
test/test_models/__init__.py
test/test_paths/__init__.py
test/test_paths/test_apikey/__init__.py
test/test_paths/test_apikey/test_get.py
test/test_paths/test_apikey_create/__init__.py
test/test_paths/test_apikey_create/test_post.py
test/test_paths/test_apikey_delete/__init__.py
test/test_paths/test_apikey_delete/test_post.py
test/test_paths/test_apikeys/__init__.py
test/test_paths/test_apikeys/test_get.py
test/test_paths/test_apikeys/test_post.py
phishing_hunter-1.0.1.dist-info/METADATA
phishing_hunter-1.0.1.dist-info/WHEEL
phishing_hunter-1.0.1.dist-info/top_level.txt
phishing_hunter-1.0.1.dist-info/RECORD
